aeons/__init__.py
aeons/aeons.py
aeons/toy_samples.py
aeons-0.0.1.dist-info/LICENSE
aeons-0.0.1.dist-info/METADATA
aeons-0.0.1.dist-info/WHEEL
aeons-0.0.1.dist-info/top_level.txt
aeons-0.0.1.dist-info/RECORD
